sockdot/__init__.py
sockdot/client.py
sockdot/events.py
sockdot/response.py
sockdot/server.py
sockdot-1.0.1.dist-info/METADATA
sockdot-1.0.1.dist-info/WHEEL
sockdot-1.0.1.dist-info/top_level.txt
sockdot-1.0.1.dist-info/RECORD
