Metadata-Version: 2.1
Name: sockdot
Version: 1.0.1
Summary: Multithreaded TCP server/client
Home-page: https://github.com/rubbiekelvin/sockdot
Author: Rubbie Kelvin
Author-email: rubbiekelvinvoltsman@gmail.com
License: MIT
Keywords: socket client server multithreaded
Platform: UNKNOWN
Classifier: Programming Language :: Python :: 3
Classifier: Operating System :: OS Independent
